MANIFEST.in
README.md
setup.py
pypeup/__init__.py
pypeup/_metaclass.py
pypeup/exceptions.py
pypeup.egg-info/PKG-INFO
pypeup.egg-info/SOURCES.txt
pypeup.egg-info/dependency_links.txt
pypeup.egg-info/requires.txt
pypeup.egg-info/top_level.txt
pypeup/_utils/__init__.py
tests/test_pipe.py