Metadata-Version: 1.0
Name: pypeup
Version: 0.9.5
Summary: An easy module for building data pipe in python.
Home-page: https://github.com/dboyliao/pypeup
Author: DboyLiao <qmalliao@gmail.com>
Author-email: qmalliao@gmail.com
License: MIT
Keywords: python data pipeline
Platform: UNKNOWN
